Metadata-Version: 2.2
Name: Mathmodule13537
Version: 0.1.0
Summary: Maths Functions
Author: Priyansh Mangla
Author-email: priyanshmangla05@gmail.com
Classifier: Programming Language :: Python :: 3
Classifier: License :: OSI Approved :: MIT License
Classifier: Operating System :: OS Independent
Requires-Python: >=3.6
Dynamic: author
Dynamic: author-email
Dynamic: classifier
Dynamic: description
Dynamic: description-content-type
Dynamic: requires-python
Dynamic: summary
